snek_game/__init__.py
snek_game/__main__.py
snek_game/action.py
snek_game/audio.py
snek_game/board.py
snek_game/drawable.py
snek_game/driver.py
snek_game/externs.py
snek_game/game.py
snek_game/handler.py
snek_game/main.py
snek_game/menu.py
snek_game/screen.py
snek_game/snek.py.tmp
snek_game/tester.py
snek_game/resources/__init__.py
snek_game/resources/data/__init__.py
snek_game/resources/levels/__init__.py
snek_game/resources/levels/lv1.txt
snek_game/resources/levels/lv10.txt
snek_game/resources/levels/lv11.txt
snek_game/resources/levels/lv12.txt
snek_game/resources/levels/lv13.txt
snek_game/resources/levels/lv14.txt
snek_game/resources/levels/lv15.txt
snek_game/resources/levels/lv16.txt
snek_game/resources/levels/lv2.txt
snek_game/resources/levels/lv3.txt
snek_game/resources/levels/lv4.txt
snek_game/resources/levels/lv5.txt
snek_game/resources/levels/lv6.txt
snek_game/resources/levels/lv7.txt
snek_game/resources/levels/lv8.txt
snek_game/resources/levels/lv8a.txt
snek_game/resources/levels/lv9.txt
snek_game/resources/levels/lvTemp.txt
snek_game/resources/levels/lvblank.txt
snek_game/resources/media/Wanks1.wav
snek_game/resources/media/__init__.py
snek_game/resources/media/bling.wav
snek_game/resources/media/block.wav
snek_game/resources/media/bloopbloop.wav
snek_game/resources/media/chomp-old1.wav
snek_game/resources/media/chomp.wav
snek_game/resources/media/chomp2.wav
snek_game/resources/media/gameOver.wav
snek_game/resources/media/levelWin.wav
snek_game/resources/media/life.wav
snek_game/resources/media/money.wav
snek_game/resources/media/music.aif
snek_game/resources/media/music.wav
snek_game/resources/media/randomnoise.wav
snek_game/resources/media/spooky.wav
snek_game/resources/media/swing.wav
snek_game-0.0.1.dist-info/METADATA
snek_game-0.0.1.dist-info/WHEEL
snek_game-0.0.1.dist-info/entry_points.txt
snek_game-0.0.1.dist-info/licenses/LICENSE
snek_game-0.0.1.dist-info/RECORD
