Metadata-Version: 2.3
Name: snek_game
Version: 0.0.1
Summary: A bad snake variant
Project-URL: Homepage, https://github.com/bkushigian/wyrm
Project-URL: Issues, https://github.com/bkushigian/wyrm/issues
Author-email: Ben Kushigian <bkushigian@gmail.com>
License-File: LICENSE
Classifier: License :: OSI Approved :: MIT License
Classifier: Operating System :: OS Independent
Classifier: Programming Language :: Python :: 3
Requires-Python: >=3.0
Requires-Dist: pygame>=2.0.0
